feedly/api_client/__init__.py
feedly/api_client/data.py
feedly/api_client/protocol.py
feedly/api_client/session.py
feedly/api_client/stream.py
feedly/api_client/utils.py
feedly/api_client/enterprise/__init__.py
feedly/api_client/enterprise/indicators_of_compromise.py
feedly/api_client/enterprise/misp_exporter.py
feedly_client-0.27.dist-info/licenses/LICENSE
feedly_client-0.27.dist-info/METADATA
feedly_client-0.27.dist-info/WHEEL
feedly_client-0.27.dist-info/top_level.txt
feedly_client-0.27.dist-info/RECORD
