Metadata-Version: 2.4
Name: feedly-client
Version: 0.27
Summary: A lightweight client for the feedly api (https://developers.feedly.com).
Home-page: https://github.com/feedly/python-api-client
Author: Feedly
Author-email: ml@feedly.com
License: MIT
Classifier: License :: OSI Approved :: MIT License
Classifier: Programming Language :: Python
Classifier: Programming Language :: Python :: 3
Classifier: Programming Language :: Python :: 3.6
Classifier: Programming Language :: Python :: Implementation :: CPython
Classifier: Programming Language :: Python :: Implementation :: PyPy
Requires-Python: >=3.6.0
License-File: LICENSE
Requires-Dist: requests>=2.19.1
Requires-Dist: backports.cached-property==1.0.1
Dynamic: author
Dynamic: author-email
Dynamic: classifier
Dynamic: description
Dynamic: description-content-type
Dynamic: home-page
Dynamic: license
Dynamic: license-file
Dynamic: requires-dist
Dynamic: requires-python
Dynamic: summary
